peptacular_bindings-0.1.1.dist-info/METADATA
peptacular_bindings-0.1.1.dist-info/WHEEL
peptacular_bindings/peptacular_bindings.cp310-win_amd64.pyd
peptacular_bindings/peptacular_bindings.cp311-win_amd64.pyd
peptacular_bindings/__init__.py
peptacular_bindings/__pycache__/__init__.cpython-310.pyc
peptacular_bindings/__pycache__/__init__.cpython-311.pyc
peptacular_bindings/peptacular_bindings.cp311-win_amd64.pyd
peptacular_bindings-0.1.1.dist-info/RECORD
